pycubeview/__init__.py
pycubeview/base_window.py
pycubeview/cli.py
pycubeview/cube_view_window.py
pycubeview/file_opening_utils.py
pycubeview/helper_functions.py
pycubeview/image_display_widget.py
pycubeview/line_roi_window.py
pycubeview/py.typed
pycubeview/spectral_display_widget.py
pycubeview/spectrum_edit_window.py
pycubeview/util_classes.py
pycubeview/utils.py
pycubeview/valid_colormaps.py
pycubeview-0.1.6.dist-info/entry_points.txt
pycubeview-0.1.6.dist-info/licenses/LICENSE
pycubeview-0.1.6.dist-info/METADATA
pycubeview-0.1.6.dist-info/WHEEL
pycubeview-0.1.6.dist-info/RECORD
