Metadata-Version: 2.4
Name: pycubeview
Version: 0.1.6
Summary: A Flexible and Interactive Spectral (and more!) Image Viewer for Python
License: LICENSE
License-File: LICENSE
Author: Z.M. Vig
Author-email: zvig@umd.edu
Requires-Python: >=3.13,<4
Classifier: License :: Other/Proprietary License
Classifier: Programming Language :: Python :: 3
Classifier: Programming Language :: Python :: 3.13
Classifier: Programming Language :: Python :: 3.14
Requires-Dist: alphashape (>=1.3.1,<2.0.0)
Requires-Dist: arguably (>=1.3.0,<2.0.0)
Requires-Dist: cmap (>=0.6.2,<0.7.0)
Requires-Dist: pandas (>=2.3.3,<3.0.0)
Requires-Dist: pandas-stubs (>=2.3.3.251201,<3.0.0.0)
Requires-Dist: pyqt6 (>=6.10.0,<7.0.0)
Requires-Dist: pyqtgraph (>=0.14.0,<0.15.0)
Requires-Dist: shapely (>=2.1.2,<3.0.0)
Requires-Dist: spectralio (>=0.1.4,<0.2.0)
Requires-Dist: types-shapely (>=2.1.0.20250917,<3.0.0.0)
